[
    {
        "url": "https://developer.aliyun.com/composer",
        "name": "developer.aliyun.com",
        "description": "",
        "country-code": "CN",
        "protocol": "https",
        "official-mirror": true
    },
    {
        "url": "https://mirrors.cloud.tencent.com/help/composer.html",
        "name": "mirrors.cloud.tencent.com",
        "description": "",
        "country-code": "CN",
        "protocol": "https",
        "official-mirror": true
    },
    {
        "url": "https://mirrors.huaweicloud.com/repository/php",
        "name": "mirrors.huaweicloud.com",
        "description": "",
        "country-code": "CN",
        "protocol": "https",
        "official-mirror": true
    },
    {
        "url": "https://packagist.co.za",
        "name": "packagist.co.za",
        "description": "",
        "country-code": "ZA",
        "protocol": "https",
        "official-mirror": true
    },
    {
        "url": "https://packagist.com.br",
        "name": "packagist.com.br",
        "description": "",
        "country-code": "BR",
        "protocol": "https",
        "official-mirror": true
    },
    {
        "url": "https://packagist.fi",
        "name": "packagist.fi",
        "description": "",
        "country-code": "FI",
        "protocol": "https",
        "official-mirror": true
    },
    {
        "url": "https://packagist.hesse.im",
        "name": "packagist.hesse.im",
        "description": "",
        "country-code": "DE",
        "protocol": "https",
        "official-mirror": true
    },
    {
        "url": "https://packagist.in",
        "name": "packagist.in",
        "description": "",
        "country-code": "IN",
        "protocol": "https",
        "official-mirror": true
    },
    {
        "url": "https://packagist.jp",
        "name": "packagist.jp",
        "description": "",
        "country-code": "JP",
        "protocol": "https",
        "official-mirror": true
    },
    {
        "url": "https://packagist.kr",
        "name": "packagist.kr",
        "description": "",
        "country-code": "KR",
        "protocol": "https",
        "official-mirror": true
    },
    {
        "url": "https://packagist.mirrors.sjtug.sjtu.edu.cn",
        "name": "packagist.mirrors.sjtug.sjtu.edu.cn",
        "description": "",
        "country-code": "CN",
        "protocol": "https",
        "official-mirror": true
    },
    {
        "url": "https://packagist.mycools.in.th/",
        "name": "packagist.mycools.in.th",
        "description": "",
        "country-code": "TH",
        "protocol": "https",
        "official-mirror": true
    },
    {
        "url": "https://packagist.phpcomposer.com",
        "name": "packagist.phpcomposer.com",
        "description": "",
        "country-code": "CN",
        "protocol": "https",
        "official-mirror": true
    },
    {
        "url": "https://packagist.phpindonesia.id",
        "name": "packagist.phpindonesia.id",
        "description": "",
        "country-code": "ID",
        "protocol": "https",
        "official-mirror": true
    },
    {
        "url": "https://packagist.tw/",
        "name": "packagist.tw",
        "description": "",
        "country-code": "TW",
        "protocol": "https",
        "official-mirror": true
    },
    {
        "url": "https://php.cnpkg.org",
        "name": "php.cnpkg.org",
        "description": "",
        "country-code": "CN",
        "protocol": "https",
        "official-mirror": true
    }
]